odds_conversions/__init__.py
odds_conversions/american_odds.py
odds_conversions/decimal_odds.py
odds_conversions/fractional_odds.py
odds_conversions/odds_conversion.py
odds_conversions/pot_odds.py
odds_conversion_tb-0.0.1.dist-info/LICENSE
odds_conversion_tb-0.0.1.dist-info/METADATA
odds_conversion_tb-0.0.1.dist-info/WHEEL
odds_conversion_tb-0.0.1.dist-info/top_level.txt
odds_conversion_tb-0.0.1.dist-info/RECORD
