Metadata-Version: 2.1
Name: odds_conversion_tb
Version: 0.0.1
Summary: This is a simple package which offers data types for odds and functions to convert between odds data type
Author-email: Thomas Brumbaugh <thomas.william.brumbaugh@gmail.com>
Project-URL: Homepage, https://github.com/pypa/odds_conversion_tb
Project-URL: Issues, https://github.com/pypa/odds_conversion_tb/issues
Classifier: Programming Language :: Python :: 3
Classifier: License :: OSI Approved :: MIT License
Classifier: Operating System :: OS Independent
Requires-Python: >=3.8
License-File: LICENSE
